searchcode/__init__.py
searchcode/connection.py
searchcode/coreutils.py
searchcode_cli-2.2.0.dist-info/LICENSE
searchcode_cli-2.2.0.dist-info/METADATA
searchcode_cli-2.2.0.dist-info/WHEEL
searchcode_cli-2.2.0.dist-info/top_level.txt
searchcode_cli-2.2.0.dist-info/RECORD
