Metadata-Version: 2.1
Name: searchcode-cli
Version: 2.2.0
Summary: A Python wrapper around the searchcode API
Author-email: Richard Mwewa <rly0nheart@duck.com>
License: GNU GENERAL PUBLIC LICENSE
Project-URL: homepage, https://searchcode.com
Project-URL: documentation, https://github.com/rly0nheart/searchcode-cli/wiki
Project-URL: repository, https://github.com/rly0nheart/searchcode-cli.git
Keywords: searchcode,search-engine,codesearch,api-wrapper
Classifier: Development Status :: 5 - Production/Stable
Classifier: Programming Language :: Python :: 3
Classifier: Intended Audience :: Information Technology
Classifier: License :: OSI Approved :: GNU General Public License v3 (GPLv3)
Classifier: Operating System :: OS Independent
Classifier: Natural Language :: English
Classifier: 
Requires-Python: >=3.9
License-File: LICENSE
